curvenote/__init__.py
curvenote/app.py
curvenote/stash.py
curvenote/version.py
curvenote-0.7.2.dist-info/LICENSE
curvenote-0.7.2.dist-info/METADATA
curvenote-0.7.2.dist-info/WHEEL
curvenote-0.7.2.dist-info/top_level.txt
curvenote-0.7.2.dist-info/RECORD
